pylgrams/__init__.py
pylgrams/grabMSdataCode.py
pylgrams/grabMzmlFunctions.py
pylgrams/grabMzxmlFunctions.py
pylgrams/example_data/LB12HL_AB.mzML.gz
pylgrams/example_data/LB12HL_AB.mzXML.gz
pylgrams/example_data/LB12HL_CD.mzML.gz
pylgrams/example_data/LB12HL_EF.mzML.gz
pylgrams/example_data/S30657.mzML.gz
pylgrams/example_data/S30657.mzXML.gz
pylgrams-1.0.1.dist-info/METADATA
pylgrams-1.0.1.dist-info/WHEEL
pylgrams-1.0.1.dist-info/licenses/LICENSE
pylgrams-1.0.1.dist-info/RECORD
