Metadata-Version: 2.3
Name: pylgrams
Version: 1.0.1
Summary: A Python-based gloss of the RaMS package in R
Project-URL: Documentation, https://github.com/wkumler/pylgrams?tab=readme-ov-file#pylgrams
Project-URL: Issues, https://github.com/wkumler/pylgrams/issues
Project-URL: Source, https://github.com/wkumler/pylgrams
Author-email: William Kumler <wkumler@uw.edu>
License-Expression: MIT
License-File: LICENSE
Keywords: GCMS,LCMS,MS,R,mass spectrometry,metabolomics,proteomics
Classifier: Development Status :: 4 - Beta
Classifier: Intended Audience :: Science/Research
Classifier: License :: OSI Approved :: MIT License
Classifier: Operating System :: OS Independent
Classifier: Programming Language :: Python
Classifier: Programming Language :: Python :: 3.9
Classifier: Programming Language :: Python :: 3.10
Classifier: Programming Language :: Python :: 3.11
Classifier: Programming Language :: Python :: 3.12
Classifier: Topic :: Scientific/Engineering :: Bio-Informatics
Requires-Python: >=3.9
Requires-Dist: lxml
Requires-Dist: numpy
Requires-Dist: pandas
Requires-Dist: tqdm
